google_analytics_client/__init__.py
google_analytics_client/client.py
google_analytics_client-0.1.2.dist-info/LICENSE
google_analytics_client-0.1.2.dist-info/WHEEL
google_analytics_client-0.1.2.dist-info/METADATA
google_analytics_client-0.1.2.dist-info/RECORD
